assignment.v
//we used 3 - 2 in 1 mux and 3 - 4 in 1 mux and 3 - full adders - 1 and
module half_adder(output s, output c, input a, input b); // internals of the half adder
xor(s, a, b);
and(c, a, b);
endmodule

module full_adder(output s, output c, input x, input y, input carry); // internals of the full adder
wire s1, c1, c2;
half_adder h1(s1, c1, x, y);
half_adder h2(s, c2, s1, carry);
or(c, c1, c2);
endmodule

module Mux2in1(output Y, input D0, D1, S); // internals of mux 2 in 1

wire T1, T2, T3;
and(T1, D1, S);
not(T2, S);
and(T3, D0, T2);
or(Y, T1, T3);
endmodule

module Mux4in1(output y,input i0, input i1, input i2 , input i3 , input s0 ,  input s1); // internals of mux 4 in 1
wire y1,y2,y3,y4,no_s0,no_s1;
not(no_s0,s0);
not(no_s1,s1);
and(y1,i0,no_s0,no_s1);
and(y2,i1,no_s0,s1);
and(y3,i2,s0,no_s1);
and(y4,i3,s0,s1);
or(y,y1,y2,y3,y4);
endmodule

module topModule_(output [2:0]G, input s0, input s1, input [2:0]a, input [2:0]b); // top module that contain all the rtl

wire mux41o , mux42o , mux43o , cout1 , cout2 , cout3 , ss, mux21o , bf1 , bf2 , bf3 , mux22o , mux23o; //wires
   
and(ss , s1 , s0); // and that makes output to mux 2 in 1 (i1) only if s1 = 0 , s0 = 0

Mux2in1 m21(mux21o , a[0] , 0 , ss);// selection of mux 2 in 1
Mux4in1 m41(mux41o ,1'b1, b[0] , ~b[0] , ~b[0] , s0 , s1);  // selection of mux 4 in 1
full_adder f1(G[0] , cout1 , mux41o , mux21o , s0 ); // add output from mux 4 in 1 + mux 2 in 1

Mux2in1 m22(mux22o , a[1] , 0 , ss);// selection of mux 2 in 1
Mux4in1 m42(mux42o ,1'b1, b[1] ,~b[1] , ~b[1] , s0 , s1);// selection of mux 4 in 1
full_adder f2(G[1] , cout2 , mux42o , mux22o , cout1); // add output from mux 4 in 1 + mux 2 in 1

Mux2in1 m23(mux23o , a[2] , 0 , ss);// selection of mux 2 in 1
Mux4in1 m43(mux43o, 1'b1, b[2] , ~b[2] , ~b[2] , s0 , s1);// selection of mux 4 in 1
full_adder f3(G[2] , cout3 , mux43o , mux23o , cout2); // add output from mux 4 in 1 + mux 2 in 1
endmodule

//testbench for the top module 
module topModule_tb();
reg s0,s1;//Input is reg s0,s1
reg [2:0]A;//Input is A 3 bit
reg [2:0]B;//Input is  B 3 bit
wire [2:0]G;//Output is G for 3 bit
topModule_ f(G, s0,s1,A,B);// making an instance
initial 
begin
$dumpfile("gtkwave.vcd");
$dumpvars(0 , topModule_tb);
$monitor("Time",$time, "| s0=%b | s1=%b | A=%b | B=%b | G=%b ", s0 , s1 , A , B , G ); // to print the output

//40-test cases
//s0 = 0 , s1 = 0;
s0=0;s1=0;A=000;B=000; 
#100 s0=0;s1=0;A=001;B=001; 
#100 s0=0;s1=0;A=010;B=010; 
#100 s0=0;s1=0;A=011;B=011; 
#100 s0=0;s1=0;A=100;B=100;
#100 s0=0;s1=0;A=101;B=111;
#100 s0=0;s1=0;A=110;B=010;
#100 s0=0;s1=0;A=111;B=101;
#100 s0=0;s1=0;A=000;B=011;
#100 s0=0;s1=0;A=001;B=111;
//s0 = 0 , s1 = 1;
#100 s0=0;s1=1;A=001;B=001;
#100 s0=0;s1=1;A=010;B=010;
#100 s0=0;s1=1;A=011;B=011;
#100 s0=0;s1=1;A=100;B=100;
#100 s0=0;s1=1;A=101;B=111;
#100 s0=0;s1=1;A=110;B=010;
#100 s0=0;s1=1;A=111;B=000;
#100 s0=0;s1=1;A=000;B=011;
#100 s0=0;s1=1;A=001;B=110;
#100 s0=0;s1=1;A=010;B=101;
//s0 = 1 , s1 = 0;
#100 s0=1;s1=0;A=001;B=001;
#100 s0=1;s1=0;A=010;B=010;
#100 s0=1;s1=0;A=011;B=011;
#100 s0=1;s1=0;A=100;B=100;
#100 s0=1;s1=0;A=101;B=111;
#100 s0=1;s1=0;A=110;B=010;
#100 s0=1;s1=0;A=111;B=000;
#100 s0=1;s1=0;A=000;B=011;
#100 s0=1;s1=0;A=001;B=110;
#100 s0=1;s1=0;A=010;B=101;
//s0 = 1 , s1 = 1;
#100 s0=1;s1=1;A=001;B=001;
#100 s0=1;s1=1;A=010;B=010;
#100 s0=1;s1=1;A=011;B=011;
#100 s0=1;s1=1;A=100;B=100;
#100 s0=1;s1=1;A=101;B=111;
#100 s0=1;s1=1;A=110;B=010;
#100 s0=1;s1=1;A=111;B=000;
#100 s0=1;s1=1;A=000;B=011;
#100 s0=1;s1=1;A=001;B=110;
#100 s0=1;s1=1;A=010;B=101;
//end
$finish;
end
endmodule

gtkwave.vcd
$date
	Sat Dec 17 15:58:02 2022
$end
$version
	Icarus Verilog
$end
$timescale
	1s
$end
$scope module topModule_tb $end
$var wire 3 ! G [2:0] $end
$var reg 3 " A [2:0] $end
$var reg 3 # B [2:0] $end
$var reg 1 $ s0 $end
$var reg 1 % s1 $end
$scope module f $end
$var wire 3 & G [2:0] $end
$var wire 3 ' a [2:0] $end
$var wire 3 ( b [2:0] $end
$var wire 1 ) cout1 $end
$var wire 1 * cout2 $end
$var wire 1 + cout3 $end
$var wire 1 , mux21o $end
$var wire 1 - mux22o $end
$var wire 1 . mux23o $end
$var wire 1 / mux41o $end
$var wire 1 0 mux42o $end
$var wire 1 1 mux43o $end
$var wire 1 2 s0 $end
$var wire 1 3 s1 $end
$var wire 1 4 ss $end
$scope module m21 $end
$var wire 1 5 D0 $end
$var wire 1 6 D1 $end
$var wire 1 4 S $end
$var wire 1 7 T1 $end
$var wire 1 8 T2 $end
$var wire 1 9 T3 $end
$var wire 1 , Y $end
$upscope $end
$scope module m41 $end
$var wire 1 : i0 $end
$var wire 1 ; i1 $end
$var wire 1 < i2 $end
$var wire 1 = i3 $end
$var wire 1 > no_s0 $end
$var wire 1 ? no_s1 $end
$var wire 1 2 s0 $end
$var wire 1 3 s1 $end
$var wire 1 / y $end
$var wire 1 @ y1 $end
$var wire 1 A y2 $end
$var wire 1 B y3 $end
$var wire 1 C y4 $end
$upscope $end
$scope module f1 $end
$var wire 1 ) c $end
$var wire 1 D c1 $end
$var wire 1 E c2 $end
$var wire 1 2 carry $end
$var wire 1 F s $end
$var wire 1 G s1 $end
$var wire 1 / x $end
$var wire 1 , y $end
$scope module h1 $end
$var wire 1 / a $end
$var wire 1 , b $end
$var wire 1 D c $end
$var wire 1 G s $end
$upscope $end
$scope module h2 $end
$var wire 1 G a $end
$var wire 1 2 b $end
$var wire 1 E c $end
$var wire 1 F s $end
$upscope $end
$upscope $end
$scope module m22 $end
$var wire 1 H D0 $end
$var wire 1 I D1 $end
$var wire 1 4 S $end
$var wire 1 J T1 $end
$var wire 1 K T2 $end
$var wire 1 L T3 $end
$var wire 1 - Y $end
$upscope $end
$scope module m42 $end
$var wire 1 M i0 $end
$var wire 1 N i1 $end
$var wire 1 O i2 $end
$var wire 1 P i3 $end
$var wire 1 Q no_s0 $end
$var wire 1 R no_s1 $end
$var wire 1 2 s0 $end
$var wire 1 3 s1 $end
$var wire 1 0 y $end
$var wire 1 S y1 $end
$var wire 1 T y2 $end
$var wire 1 U y3 $end
$var wire 1 V y4 $end
$upscope $end
$scope module f2 $end
$var wire 1 * c $end
$var wire 1 W c1 $end
$var wire 1 X c2 $end
$var wire 1 ) carry $end
$var wire 1 Y s $end
$var wire 1 Z s1 $end
$var wire 1 0 x $end
$var wire 1 - y $end
$scope module h1 $end
$var wire 1 0 a $end
$var wire 1 - b $end
$var wire 1 W c $end
$var wire 1 Z s $end
$upscope $end
$scope module h2 $end
$var wire 1 Z a $end
$var wire 1 ) b $end
$var wire 1 X c $end
$var wire 1 Y s $end
$upscope $end
$upscope $end
$scope module m23 $end
$var wire 1 [ D0 $end
$var wire 1 \ D1 $end
$var wire 1 4 S $end
$var wire 1 ] T1 $end
$var wire 1 ^ T2 $end
$var wire 1 _ T3 $end
$var wire 1 . Y $end
$upscope $end
$scope module m43 $end
$var wire 1 ` i0 $end
$var wire 1 a i1 $end
$var wire 1 b i2 $end
$var wire 1 c i3 $end
$var wire 1 d no_s0 $end
$var wire 1 e no_s1 $end
$var wire 1 2 s0 $end
$var wire 1 3 s1 $end
$var wire 1 1 y $end
$var wire 1 f y1 $end
$var wire 1 g y2 $end
$var wire 1 h y3 $end
$var wire 1 i y4 $end
$upscope $end
$scope module f3 $end
$var wire 1 + c $end
$var wire 1 j c1 $end
$var wire 1 k c2 $end
$var wire 1 * carry $end
$var wire 1 l s $end
$var wire 1 m s1 $end
$var wire 1 1 x $end
$var wire 1 . y $end
$scope module h1 $end
$var wire 1 1 a $end
$var wire 1 . b $end
$var wire 1 j c $end
$var wire 1 m s $end
$upscope $end
$scope module h2 $end
$var wire 1 m a $end
$var wire 1 * b $end
$var wire 1 k c $end
$var wire 1 l s $end
$upscope $end
$upscope $end
$upscope $end
$upscope $end
$enddefinitions $end
#0
$dumpvars
1m
1l
0k
0j
0i
0h
0g
1f
1e
1d
1c
1b
0a
1`
0_
1^
0]
0\
0[
1Z
1Y
0X
0W
0V
0U
0T
1S
1R
1Q
1P
1O
0N
1M
0L
1K
0J
0I
0H
1G
1F
0E
0D
0C
0B
0A
1@
1?
1>
1=
1<
0;
1:
09
18
07
06
05
04
03
02
11
10
1/
0.
0-
0,
0+
0*
0)
b0 (
b0 '
b111 &
0%
0$
b0 #
b0 "
b111 !
$end
#100
1+
0l
1k
1*
0Y
1X
0F
b0 !
b0 &
1)
0G
1D
1,
0<
0=
19
1;
15
b1 #
b1 (
b1 "
b1 '
#200
1F
0)
0Y
b1 !
b1 &
0X
1G
0D
0Z
1W
0,
1-
1<
1=
0O
0P
09
1L
0;
1N
05
1H
b10 #
b10 (
b10 "
b10 '
#300
1Y
0F
b10 !
b10 &
1)
0G
1D
1,
0<
0=
19
1;
15
b11 #
b11 (
b11 "
b11 '
#400
1F
0)
1Y
0X
0*
0l
b11 !
b11 &
0k
1G
0D
1Z
0W
0m
1j
0,
0-
1.
1<
1=
1O
1P
0b
0c
09
0L
1_
0;
0N
1a
05
0H
1[
b100 #
b100 (
b100 "
b100 '
#500
1l
1*
0Y
1X
0F
b100 !
b100 &
1)
0G
1D
1,
0<
0=
0O
0P
19
1;
1N
15
b111 #
b111 (
b101 "
b101 '
#600
1F
0)
0Y
b101 !
b101 &
0X
1G
0D
0Z
1W
0,
1-
1<
1=
1b
1c
09
1L
0;
0a
05
1H
b10 #
b10 (
b110 "
b110 '
#700
1Y
0F
b110 !
b110 &
1)
0G
1D
1,
0<
0=
1O
1P
0b
0c
19
1;
0N
1a
15
b101 #
b101 (
b111 "
b111 '
#800
1F
0)
1Y
0X
0*
1l
b111 !
b111 &
0k
0+
1G
0D
1Z
0W
1m
0j
0,
0-
0.
0O
0P
1b
1c
09
0L
0_
1N
0a
05
0H
0[
b11 #
b11 (
b0 "
b0 '
#900
1+
0l
1k
1*
0Y
1X
0F
b0 !
b0 &
1)
0G
1D
1,
0b
0c
19
1a
15
b111 #
b111 (
b1 "
b1 '
#1000
0*
0+
1Y
0X
0l
b10 !
b10 &
0k
0Z
0m
00
01
1O
1P
1b
1c
0@
0S
0f
0N
0a
0?
1A
0R
0T
0e
0g
b1 #
b1 (
1%
13
#1100
0Y
1l
b100 !
b100 &
0)
1*
0D
1W
0/
10
0,
1-
0A
1<
1=
1T
0O
0P
09
1L
0;
1N
05
1H
b10 #
b10 (
b10 "
b10 '
#1200
1Y
b110 !
b110 &
1)
1D
1/
1,
1A
0<
0=
19
1;
15
b11 #
b11 (
b11 "
b11 '
#1300
0Y
0l
b0 !
b0 &
0)
0*
1+
0D
0W
1j
0/
00
11
0,
0-
1.
0A
1<
1=
0T
1O
1P
1g
0b
0c
09
0L
1_
0;
0N
1a
05
0H
1[
b100 #
b100 (
b100 "
b100 '
#1400
1l
b100 !
b100 &
1*
1X
1)
1Z
1D
1/
10
1,
1A
0<
0=
1T
0O
0P
19
1;
1N
15
b111 #
b111 (
b101 "
b101 '
#1500
0l
1k
1+
0)
0Y
b0 !
b0 &
0X
1m
0j
0D
0Z
1W
0/
01
0,
1-
0A
1<
1=
0g
1b
1c
09
1L
0;
0a
05
1H
b10 #
b10 (
b110 "
b110 '
#1600
0+
1l
0k
1Y
0*
1F
b111 !
b111 &
1Z
0W
1G
00
1,
0T
1O
1P
19
0N
15
b0 #
b0 (
b111 "
b111 '
#1700
0l
b11 !
b11 &
0m
1/
10
0,
0-
0.
1A
0<
0=
1T
0O
0P
09
0L
0_
1;
1N
05
0H
0[
b11 #
b11 (
b0 "
b0 '
#1800
1l
b111 !
b111 &
1m
0/
11
1,
0A
1<
1=
1g
0b
0c
19
0;
1a
15
b110 #
b110 (
b1 "
b1 '
#1900
1/
00
0,
1-
1A
0<
0=
0T
1O
1P
09
1L
1;
0N
05
1H
b101 #
b101 (
b10 "
b10 '
#2000
1+
0l
1k
1*
1h
1,
0-
1G
10
1m
0Y
1X
1b
1c
19
0L
0/
1U
11
1)
0a
15
0H
1?
0A
1R
1e
0g
0>
0F
b0 !
b0 &
1E
0Q
0d
b1 #
b1 (
b1 "
b1 '
0%
03
1$
12
#2100
1+
0l
1k
1)
1*
0F
1E
0Y
b0 !
b0 &
1X
1/
00
1G
1Z
0W
1B
0U
0,
1-
1<
1=
0O
0P
09
1L
0;
1N
05
1H
b10 #
b10 (
b10 "
b10 '
#2200
1+
0l
1k
1*
0Y
1X
1)
0F
b0 !
b0 &
1E
0/
1G
0D
0B
1,
0<
0=
19
1;
15
b11 #
b11 (
b11 "
b11 '
#2300
1)
1*
1+
0F
1E
0Y
1X
0l
b0 !
b0 &
1k
1/
10
01
1G
1Z
1m
0j
1B
1U
0h
0,
0-
1.
1<
1=
1O
1P
0b
0c
09
0L
1_
0;
0N
1a
05
0H
1[
b100 #
b100 (
b100 "
b100 '
#2400
0+
1Y
1l
0k
0*
0X
1)
0Z
0F
b110 !
b110 &
1E
0/
00
1G
0D
0B
0U
1,
0<
0=
0O
0P
19
1;
1N
15
b111 #
b111 (
b101 "
b101 '
#2500
1l
1+
1)
1*
0m
1j
0F
1E
0Y
b100 !
b100 &
1X
1/
11
1G
1Z
1B
1h
0,
1-
1<
1=
1b
1c
09
1L
0;
0a
05
1H
b10 #
b10 (
b110 "
b110 '
#2600
1Y
0X
0Z
1W
1F
b111 !
b111 &
0E
10
0G
1D
1U
1,
1O
1P
19
0N
15
b0 #
b0 (
b111 "
b111 '
#2700
1F
0E
0)
0Y
0X
0*
1l
b101 !
b101 &
0k
0+
0/
00
0G
0D
0Z
0W
1m
0j
0B
0U
0,
0-
0.
0<
0=
0O
0P
09
0L
0_
1;
1N
05
0H
0[
b11 #
b11 (
b0 "
b0 '
#2800
1Y
0l
1)
1D
0m
1F
b11 !
b11 &
0E
1/
01
0G
1B
0h
1,
1<
1=
0b
0c
19
0;
1a
15
b110 #
b110 (
b1 "
b1 '
#2900
1l
1*
1W
1F
0E
0)
0Y
b101 !
b101 &
0X
0/
10
0G
0D
0Z
0B
1U
0,
1-
0<
0=
1O
1P
09
1L
1;
0N
05
1H
b101 #
b101 (
b10 "
b10 '
#3000
1m
1Y
b111 !
b111 &
0*
11
1Z
0W
1i
0-
1b
1c
0L
08
0K
0^
0U
0a
15
0H
14
0?
0R
1V
0e
b1 #
b1 (
b1 "
b1 '
1%
13
#3100
1)
0F
1E
1Y
b110 !
b110 &
1G
0Z
1/
00
1C
0V
1<
1=
0O
0P
0;
1N
05
1H
b10 #
b10 (
b10 "
b10 '
#3200
0Y
0)
1F
b101 !
b101 &
0E
0G
0/
0C
0<
0=
1;
15
b11 #
b11 (
b11 "
b11 '
#3300
1*
1X
1)
0F
1E
0Y
1l
b100 !
b100 &
1G
1Z
0m
1/
10
01
1C
1V
0i
1<
1=
1O
1P
0b
0c
0;
0N
1a
05
0H
1[
b100 #
b100 (
b100 "
b100 '
#3400
0l
0)
0*
1F
0E
0Y
b1 !
b1 &
0X
0G
0Z
0/
00
0C
0V
0<
0=
0O
0P
1;
1N
15
b111 #
b111 (
b101 "
b101 '
#3500
1Y
1)
0F
1E
1l
b110 !
b110 &
1G
1m
1/
11
1C
1i
1<
1=
1b
1c
0;
0a
05
1H
b10 #
b10 (
b110 "
b110 '
#3600
1+
0l
1k
1*
0Y
b0 !
b0 &
1X
1Z
10
1V
1O
1P
0N
15
b0 #
b0 (
b111 "
b111 '
#3700
0+
1l
0k
0)
0*
1F
0E
0Y
b101 !
b101 &
0X
0G
0Z
0/
00
0C
0V
0<
0=
0O
0P
1;
1N
05
0H
0[
b11 #
b11 (
b0 "
b0 '
#3800
1Y
1)
0F
1E
0l
b10 !
b10 &
1G
0m
1/
01
1C
0i
1<
1=
0b
0c
0;
1a
15
b110 #
b110 (
b1 "
b1 '
#3900
0l
0)
0*
1F
0E
1Y
b11 !
b11 &
0X
0G
1Z
0/
10
0C
1V
0<
0=
1O
1P
1;
0N
05
1H
b101 #
b101 (
b10 "
b10 '
